tipey/__init__.py
tipey/quantity.py
tipey/unit/__init__.py
tipey/unit/base_units.py
tipey/unit/currency.py
tipey/unit/mass.py
tipey/unit/temperature.py
tipey-0.0.2.dist-info/LICENSE
tipey-0.0.2.dist-info/METADATA
tipey-0.0.2.dist-info/WHEEL
tipey-0.0.2.dist-info/top_level.txt
tipey-0.0.2.dist-info/RECORD
