Metadata-Version: 2.1
Name: tipey
Version: 0.0.2
Summary: A package for units, types and conversions.
Author: David Lassner
License: MIT License        
Project-URL: Homepage, https://github.com/millawell/tipey
Project-URL: Bug Tracker, https://github.com/millawell/tipey/issues
Classifier: Programming Language :: Python :: 3
Classifier: License :: OSI Approved :: MIT License
Classifier: Operating System :: OS Independent
Requires-Python: >=3.7
License-File: LICENSE
Requires-Dist: scipy
Requires-Dist: currencyconverter
